scredits/__init__.py
scredits/__main__.py
scredits/__version__.py
scredits/cli.py
scredits/config.py
scredits/scredits.py
scredits-1.4.dist-info/LICENSE
scredits-1.4.dist-info/METADATA
scredits-1.4.dist-info/WHEEL
scredits-1.4.dist-info/entry_points.txt
scredits-1.4.dist-info/top_level.txt
scredits-1.4.dist-info/RECORD
