Metadata-Version: 2.1
Name: scredits
Version: 1.4
Summary: A tool to retrieve and display Slurm usage data
Home-page: https://github.com/giuliolibrando/slurm-scredits
Author: Giulio Librando
Author-email: giuliolibrando@gmail.com
License: UNKNOWN
Platform: UNKNOWN
Classifier: Programming Language :: Python :: 3
Classifier: License :: OSI Approved :: MIT License
Classifier: Operating System :: OS Independent
Requires-Python: >=3.6
License-File: LICENSE
Requires-Dist: pandas
